{"leaderboard":{"snaquaza":{"points":25,"name":"Snaquaza"},"whirlwindbulbasaur":{"points":1500,"name":"WhirlwindBulbasaur"},"coolthing":{"points":75,"name":"coolthing"},"embar":{"points":50,"name":"Embar"},"zygardeorder":{"points":25,"name":"Zygardeorder"},"moonlightwizard":{"points":3500,"name":"MOONLIGHTWIZARD"},"crzycookie":{"points":25,"name":"Crzy♫Cookie"},"serponge":{"points":500,"name":"Serponge"},"abd1710":{"points":500,"name":"abd1710"},"repenting":{"points":500,"name":"Re+pen÷ting=❤"},"youhavelostperiod":{"points":500,"name":"youhavelostperiod"},"moo":{"points":1500,"name":"Moo"},"flyingkebab":{"points":1000,"name":"Flying Kebab"},"chatterseel":{"points":500,"name":"chatterseel."},"broil":{"points":500,"name":"broil"}}}